{"elapsed":"1.083","endpoint-url":"https://tewkesburybc.s3.eu-west-2.amazonaws.com/geojson/tree-preservation-zone.geojson","entry-date":"2024-02-11T00:19:16.435366","request-headers":{"Accept":"*/*","Accept-Encoding":"gzip, deflate","Connection":"keep-alive","User-Agent":"DLUHC Digital Land"},"resource":"e4e45d88b8d0ff9c015d60b8bf4ed94a0000a811d08416f45d279d8f03af61ab","response-headers":{"Accept-Ranges":"bytes","Content-Length":"1514702","Content-Type":"binary/octet-stream","Date":"Sun, 11 Feb 2024 00:21:41 GMT","ETag":"\"007a1707ad66e04472e409c1c0ae9bc2\"","Last-Modified":"Mon, 05 Feb 2024 10:30:27 GMT","Server":"AmazonS3","x-amz-id-2":"d9bIstGwqMmszqU3UputPFS/4/TlRQYvmU3Hjmn/AkjoWnt4z92e1S2rcrhlcWNxdJRO9J5X83k=","x-amz-request-id":"MSWRJMQSH88SZ8G1","x-amz-server-side-encryption":"AES256","x-amz-version-id":"u65U3k3xshKVEroQcCsSTdpp5s8DiWx2"},"ssl-verify":true,"status":"200"}