{"elapsed":"1.062","endpoint-url":"https://opendata.arcgis.com/datasets/a4ddbb5114274ba89e33a33545c407c8_0.geojson","entry-date":"2023-02-08T00:15:24.732789","request-headers":{"Accept":"*/*","Accept-Encoding":"gzip, deflate","Connection":"keep-alive","User-Agent":"DLUHC Digital Land"},"resource":"f222a072f6b151f615b8b5d6ca9d8c316570eecc046445d7894dbe4ac6deb110","response-headers":{"Cache-Control":"must-revalidate","Connection":"keep-alive","Content-Disposition":"attachment; filename=\"Tree_Preservation_Orders.geojson\"","Content-Encoding":"gzip","Content-Length":"4378446","Content-Security-Policy":"upgrade-insecure-requests","Content-Type":"application/json","Date":"Wed, 08 Feb 2023 00:15:28 GMT","ETag":"\"d110e5efc62eb2aa9658c472a1c6d982\"","Last-Modified":"Tue, 07 Feb 2023 00:17:54 GMT","Server":"openresty","Strict-Transport-Security":"max-age=31536000","Vary":"Accept-Encoding","X-Content-Type-Options":"nosniff","x-amz-meta-cachetime":"6919"},"ssl-verify":true,"status":"200"}