{"elapsed":"0.888","endpoint-url":"https://opendata.arcgis.com/datasets/a4ddbb5114274ba89e33a33545c407c8_0.geojson","entry-date":"2023-05-04T00:14:34.535462","request-headers":{"Accept":"*/*","Accept-Encoding":"gzip, deflate","Connection":"keep-alive","User-Agent":"DLUHC Digital Land"},"resource":"d79f06c55dbab7b091ac2635362895762a59dde3d63c3388efc19c83c2479565","response-headers":{"Cache-Control":"must-revalidate","Connection":"keep-alive","Content-Disposition":"attachment; filename=\"Tree_Preservation_Orders.geojson\"","Content-Encoding":"gzip","Content-Length":"4378144","Content-Security-Policy":"upgrade-insecure-requests","Content-Type":"application/json","Date":"Thu, 04 May 2023 00:14:37 GMT","ETag":"\"c9e5a32df9efc9a0c8da79116145fb12\"","Last-Modified":"Wed, 03 May 2023 00:20:16 GMT","Server":"openresty","Strict-Transport-Security":"max-age=31536000","Vary":"Accept-Encoding","X-Content-Type-Options":"nosniff","x-amz-meta-cachetime":"4865","x-amz-server-side-encryption":"AES256"},"ssl-verify":true,"status":"200"}