{"elapsed":"2.858","endpoint-url":"https://opendata.arcgis.com/datasets/a4ddbb5114274ba89e33a33545c407c8_0.geojson","entry-date":"2023-06-18T00:17:14.351932","request-headers":{"Accept":"*/*","Accept-Encoding":"gzip, deflate","Connection":"keep-alive","User-Agent":"DLUHC Digital Land"},"resource":"768bbbc060d908f7bffcb1096f0c1a0bee658e4f4d06d4d39cab2eea58469a97","response-headers":{"Cache-Control":"must-revalidate","Connection":"keep-alive","Content-Disposition":"attachment; filename=\"Tree_Preservation_Orders.geojson\"","Content-Encoding":"gzip","Content-Length":"4378171","Content-Security-Policy":"upgrade-insecure-requests","Content-Type":"application/json","Date":"Sun, 18 Jun 2023 00:17:22 GMT","ETag":"\"28ea0a711f287e9d38460a5d70a84a59\"","Last-Modified":"Fri, 16 Jun 2023 00:16:40 GMT","Strict-Transport-Security":"max-age=31536000","Vary":"Accept-Encoding","X-Content-Type-Options":"nosniff","x-amz-meta-cachetime":"5277","x-amz-server-side-encryption":"AES256"},"ssl-verify":true,"status":"200"}