{"elapsed":"0.287","endpoint-url":"https://raw.githubusercontent.com/digital-land/tree-preservation-order-collection/main/data/Southwark/TPO%20zones%20-%20Area%20type.zip","entry-date":"2023-09-11T00:15:17.406835","request-headers":{"Accept":"*/*","Accept-Encoding":"gzip, deflate","Connection":"keep-alive","User-Agent":"DLUHC Digital Land"},"resource":"f9c98a7bb2fe99b4fffb86a5d8f4d840119f6fa72c7b2876ed5dac7d78fa39bf","response-headers":{"Accept-Ranges":"bytes","Access-Control-Allow-Origin":"*","Cache-Control":"max-age=300","Connection":"keep-alive","Content-Length":"23511","Content-Security-Policy":"default-src 'none'; style-src 'unsafe-inline'; sandbox","Content-Type":"application/zip","Cross-Origin-Resource-Policy":"cross-origin","Date":"Mon, 11 Sep 2023 00:15:19 GMT","ETag":"W/\"932feb2252fb15f62452286232f33c3c0b8312d0cca7b4ca38c786118afb8e36\"","Expires":"Mon, 11 Sep 2023 00:20:19 GMT","Source-Age":"0","Strict-Transport-Security":"max-age=31536000","Vary":"Authorization,Accept-Encoding,Origin","Via":"1.1 varnish","X-Cache":"MISS","X-Cache-Hits":"0","X-Content-Type-Options":"nosniff","X-Fastly-Request-ID":"df8989ba17248e38131a0a5614ac9d20050a978f","X-Frame-Options":"deny","X-GitHub-Request-Id":"2E5C:3FB1:D8931:107C4F:64FE5C16","X-Served-By":"cache-sjc1000143-SJC","X-Timer":"S1694391319.964556,VS0,VE174","X-XSS-Protection":"1; mode=block"},"ssl-verify":true,"status":"200"}