{"elapsed":"1.05","endpoint-url":"https://services-eu1.arcgis.com/xk4RA36G57mVH7Aw/ArcGIS/rest/services/TPO_National_Planning_Map_view/FeatureServer/1/query?where=1%3D1&f=geojson&outFields=*","entry-date":"2023-12-25T00:15:38.576767","request-headers":{"Accept":"*/*","Accept-Encoding":"gzip, deflate","Connection":"keep-alive","User-Agent":"DLUHC Digital Land"},"resource":"9cfd6db00085a095e2941384fb474d87de3456c03e44ffac92bdf11596ec95c8","response-headers":{"Access-Control-Allow-Origin":"*","Cache-Control":"public, max-age=30, s-maxage=30","Connection":"keep-alive","Content-Encoding":"gzip","Content-Length":"287981","Content-Type":"application/json; charset=utf-8","Date":"Mon, 25 Dec 2023 00:23:21 GMT","ETag":"sd877_326016231","Last-Modified":"Sun, 24 Dec 2023 21:27:18 GMT","Request-Context":"appId=cid-v1:9d64e4d7-d1be-4f53-9050-c2517b09882e","Vary":"X-Esri-Authorization","Via":"1.1 b57909894838e27c3bff2a0828c2639c.cloudfront.net (CloudFront)","X-Amz-Cf-Id":"3suUp-OHbssQIAzYSRrXY82J7MSiq7rmuqfyrTKWIdRLV2hoMZwFIg==","X-Amz-Cf-Pop":"ORD53-C3","X-ArcGIS-Correlation-Id":"00-24e9c02b2fbf80f46c433884e9c2a8aa-25c38041fe5ec579-00","X-ArcGIS-Instance":"od2z6srwj00000U","X-ArcGIS-Trace-Id":"24e9c02b2fbf80f46c433884e9c2a8aa","X-Cache":"Miss from cloudfront","x-arcgis-upstream":"eu1h00c00","x-esri-org-request-units-per-min":"usage=4;max=6000","x-esri-query-geometry-field-name":"SHAPE","x-esri-query-max-vertex-count":"105","x-esri-query-request-units":"2","x-esri-tiles-basic-query-mode":"true","x-esri-tiles-basic-query-type":"Basic"},"ssl-verify":true,"status":"200"}