{"bytes":145115,"elapsed":"0.364","endpoint-url":"https://raw.githubusercontent.com/digital-land/tree-preservation-order-collection/main/data/Southwark/TPO%20zones%20-%20Individual%20type.zip","entry-date":"2021-12-19T00:24:07.049210","request-headers":{"Accept":"*/*","Accept-Encoding":"gzip, deflate","Connection":"keep-alive","User-Agent":"DLUHC Digital Land"},"resource":"cab148c36aaec04f795c14ab88b2bba4b1d713578d17dab1b5e4d782ee78b705","response-headers":{"Accept-Ranges":"bytes","Access-Control-Allow-Origin":"*","Cache-Control":"max-age=300","Connection":"keep-alive","Content-Length":"145115","Content-Security-Policy":"default-src 'none'; style-src 'unsafe-inline'; sandbox","Content-Type":"application/zip","Date":"Sun, 19 Dec 2021 00:24:10 GMT","ETag":"W/\"6dcfd3436d162fc8e7a00a102f35403aecc533197c9595c86206be49d5906850\"","Expires":"Sun, 19 Dec 2021 00:29:10 GMT","Source-Age":"0","Strict-Transport-Security":"max-age=31536000","Vary":"Authorization,Accept-Encoding,Origin","Via":"1.1 varnish","X-Cache":"MISS","X-Cache-Hits":"0","X-Content-Type-Options":"nosniff","X-Fastly-Request-ID":"76278a975dd9908cc538b62c5a328db1798fcac0","X-Frame-Options":"deny","X-GitHub-Request-Id":"A654:4480:8B2D1E:C1A9F6:61BE7BA9","X-Served-By":"cache-sea4467-SEA","X-Timer":"S1639873450.670398,VS0,VE348","X-XSS-Protection":"1; mode=block"},"ssl-verify":true,"status":"200"}